{
  "services": [
    {
      "id": 1,
      "name": "Computer Support",
      "services": [
        "Computer Repairs",
        "Computer Setup",
        "Laptop Repairs",
        "Mac Repairs",
        "Computer Cleaning",
        "Computer Troubleshooting",
        "Computer Upgrades & Hardware Installation",
        "Computer Hardware Repair",
        "Software Installation & Setup",
        "Data Recovery",
        "Data Backup & Transfer",
        "Virus, Spyware & Malware Removal",
        "Insurance Reports",
        "Tech Training"
      ]
    },
    {
      "id": 2,
      "name": "Mobile & Tablets",
      "services": [
        "Mobile Device Setup",
        "Tablet Repairs",
        "New tablet set up and training",
        "Install and recommend apps",
        "Fix slow iPad and tablet",
        "Troubleshoot frozen screens"
      ]
    },
    {
      "id": 3,
      "name": "Wi-Fi & Network",
      "services": [
        "Computer & Network Security",
        "Wi-Fi & Internet Setup",
        "Setup new wireless network",
        "Troubleshoot slow internet",
        "Boost weak Wi-Fi signals",
        "Connect new devices to network",
        "Network security setup"
      ]
    },
    {
      "id": 4,
      "name": "Other Services",
      "services": [
        "TV Wall Mounting",
        "Printer Setup",
        "Point of Sale Setup",
        "Digital Security Check",
        "Smart Home Setup",
        "Email Setup & Troubleshooting",
        "Smart TV Setup"
      ]
    }
  ]
} 